multianalyzer/_multianalyzer.pypy310-pp73-x86_64-linux-gnu.so
multianalyzer/multianalyzer.cl
multianalyzer/timer.py
multianalyzer/version.py
multianalyzer/__init__.py
multianalyzer/opencl.py
multianalyzer/utils.py
multianalyzer/file_io.py
multianalyzer/app/__init__.py
multianalyzer/app/rebin.py
multianalyzer/test/test_parser.py
multianalyzer/test/__init__.py
multianalyzer/test/test_all.py
multianalyzer-0.7.0.dist-info/RECORD
multianalyzer-0.7.0.dist-info/copyright
multianalyzer-0.7.0.dist-info/METADATA
multianalyzer-0.7.0.dist-info/entry_points.txt
multianalyzer-0.7.0.dist-info/WHEEL
multianalyzer.libs/libgomp-a34b3233.so.1.0.0
