Metadata-Version: 2.1
Name: multianalyzer
Version: 0.7.0
Summary: Rebinning of powder diffraction data taken with multiple analyzer crystals and a large area detector
Author-Email: =?utf-8?q?J=C3=A9r=C3=B4me_Kieffer?= <jerome.kieffer@esrf.fr>
License: Format: http://www.debian.org/doc/packaging-manuals/copyright-format/1.0/
Classifier: Development Status :: 5 - Production/Stable
Classifier: Environment :: Console
Classifier: Intended Audience :: End Users/Desktop
Classifier: Intended Audience :: Developers
Classifier: Intended Audience :: Science/Research
Classifier: License :: OSI Approved :: MIT License
Classifier: Operating System :: MacOS :: MacOS X
Classifier: Operating System :: Microsoft :: Windows
Classifier: Operating System :: POSIX
Classifier: Programming Language :: C
Classifier: Programming Language :: Cython
Classifier: Programming Language :: Python
Classifier: Programming Language :: Python :: 3
Classifier: Programming Language :: Python :: Implementation :: CPython
Classifier: Topic :: Scientific/Engineering :: Chemistry
Classifier: Topic :: Scientific/Engineering :: Bio-Informatics
Classifier: Topic :: Scientific/Engineering :: Physics
Classifier: Topic :: Software Development :: Libraries :: Python Modules
Project-URL: homepage, https://pypi.org/project/multianalyzer/
Project-URL: source, https://github.com/kif/multianalyzer
Project-URL: download, https://github.com/kif/multianalyzer/releases
Project-URL: tracker, https://github.com/kif/multianalyzer/issues
Requires-Python: >=3.7
Requires-Dist: numpy
Requires-Dist: h5py
Requires-Dist: pyopencl
